spectrepy.py
spectrepy-0.1.0.dist-info/LICENSE.md
spectrepy-0.1.0.dist-info/METADATA
spectrepy-0.1.0.dist-info/WHEEL
spectrepy-0.1.0.dist-info/RECORD
